BubbleID/BubbleID.py
BubbleID/__init__.py
BubbleID/ocsort/__init__.py
BubbleID/ocsort/association.py
BubbleID/ocsort/kalmanfilter.py
BubbleID/ocsort/ocsort.py
bubbleid-0.0.9.dist-info/LICENSE.txt
bubbleid-0.0.9.dist-info/METADATA
bubbleid-0.0.9.dist-info/WHEEL
bubbleid-0.0.9.dist-info/top_level.txt
bubbleid-0.0.9.dist-info/RECORD
