Metadata-Version: 2.1
Name: bubbleid
Version: 0.0.9
Summary: BubbleID Framework
Home-page: https://github.com/cldunlap73/BubbleID
Author: cldunlap
Author-email: christydunlap26@gmail.com
License: Apache-2.0
Classifier: License :: OSI Approved :: Apache Software License
License-File: LICENSE.txt
